nemo_nlp/__init__.py
nemo_nlp/data/__init__.py
nemo_nlp/data/data_layers.py
nemo_nlp/data/utils.py
nemo_nlp/data/datasets/__init__.py
nemo_nlp/data/datasets/bert_pretraining.py
nemo_nlp/data/datasets/glue.py
nemo_nlp/data/datasets/joint_intent_slot.py
nemo_nlp/data/datasets/language_modeling.py
nemo_nlp/data/datasets/sentence_classification.py
nemo_nlp/data/datasets/token_classification.py
nemo_nlp/data/datasets/translation.py
nemo_nlp/data/datasets/utils.py
nemo_nlp/data/tokenizers/__init__.py
nemo_nlp/data/tokenizers/bert_tokenizer.py
nemo_nlp/data/tokenizers/char_tokenizer.py
nemo_nlp/data/tokenizers/gpt2_tokenizer.py
nemo_nlp/data/tokenizers/spc_tokenizer.py
nemo_nlp/data/tokenizers/tokenizer_spec.py
nemo_nlp/data/tokenizers/word_tokenizer.py
nemo_nlp/data/tokenizers/yttm_tokenizer.py
nemo_nlp/huggingface/__init__.py
nemo_nlp/huggingface/bert.py
nemo_nlp/modules/__init__.py
nemo_nlp/modules/classifiers.py
nemo_nlp/modules/losses.py
nemo_nlp/modules/pytorch_utils.py
nemo_nlp/modules/transformer_nm.py
nemo_nlp/transformer/__init__.py
nemo_nlp/transformer/decoders.py
nemo_nlp/transformer/encoders.py
nemo_nlp/transformer/generators.py
nemo_nlp/transformer/modules.py
nemo_nlp/transformer/utils.py
nemo_nlp/utils/__init__.py
nemo_nlp/utils/nlp_utils.py
nemo_nlp/utils/callbacks/__init__.py
nemo_nlp/utils/callbacks/bert_pretraining.py
nemo_nlp/utils/callbacks/glue.py
nemo_nlp/utils/callbacks/joint_intent_slot.py
nemo_nlp/utils/callbacks/language_modeling.py
nemo_nlp/utils/callbacks/sentence_classification.py
nemo_nlp/utils/callbacks/token_classification.py
nemo_nlp/utils/callbacks/translation.py
nemo_nlp/utils/metrics/__init__.py
nemo_nlp/utils/metrics/bleu.py
nemo_nlp/utils/metrics/fairseq_tokenizer.py
nemo_nlp/utils/metrics/sacrebleu.py
nemo_nlp-0.9.0.dist-info/LICENSE
nemo_nlp-0.9.0.dist-info/METADATA
nemo_nlp-0.9.0.dist-info/WHEEL
nemo_nlp-0.9.0.dist-info/top_level.txt
nemo_nlp-0.9.0.dist-info/RECORD
