Metadata-Version: 2.1
Name: nemo-nlp
Version: 0.9.0
Summary: Collection of Neural Modules for Natural Language Processing
Home-page: https://github.com/nvidia/nemo
Author: NVIDIA
Author-email: nemo-toolkit@nvidia.com
License: UNKNOWN
Platform: UNKNOWN
Classifier: Programming Language :: Python :: 3
Classifier: Operating System :: OS Independent
Classifier: License :: OSI Approved :: Apache Software License
Requires-Dist: nemo-toolkit
Requires-Dist: torchtext
Requires-Dist: sentencepiece
Requires-Dist: python-dateutil (<2.8.1,>=2.1)
Requires-Dist: boto3
Requires-Dist: unidecode
Requires-Dist: pytorch-transformers
Requires-Dist: matplotlib
Requires-Dist: h5py
Requires-Dist: youtokentome
